{"departamento": {"bn": {"porcentaje": {"sospechosos": "0.00", "descartados": "17.55", "recuperados": "0.15", "confirmados": "77.00", "decesos": "5.30"}, "total": 661, "contador": {"sospechosos": 0, "descartados": 116, "recuperados": 1, "confirmados": 509, "decesos": 35}}, "or": {"porcentaje": {"sospechosos": "0.00", "descartados": "61.21", "recuperados": "12.24", "confirmados": "24.86", "decesos": "1.69"}, "total": 531, "contador": {"sospechosos": 0, "descartados": 325, "recuperados": 65, "confirmados": 132, "decesos": 9}}, "tj": {"porcentaje": {"sospechosos": "8.70", "descartados": "68.12", "recuperados": "2.90", "confirmados": "18.84", "decesos": "1.45"}, "total": 69, "contador": {"sospechosos": 6, "descartados": 47, "recuperados": 2, "confirmados": 13, "decesos": 1}}, "lp": {"porcentaje": {"sospechosos": "0.18", "descartados": "80.40", "recuperados": "4.44", "confirmados": "14.15", "decesos": "0.83"}, "total": 2276, "contador": {"sospechosos": 4, "descartados": 1830, "recuperados": 101, "confirmados": 322, "decesos": 19}}, "cb": {"porcentaje": {"sospechosos": "0.00", "descartados": "82.51", "recuperados": "3.53", "confirmados": "13.33", "decesos": "0.63"}, "total": 1275, "contador": {"sospechosos": 0, "descartados": 1052, "recuperados": 45, "confirmados": 170, "decesos": 8}}, "pn": {"porcentaje": {"sospechosos": "0.00", "descartados": "78.95", "recuperados": "7.37", "confirmados": "12.63", "decesos": "1.05"}, "total": 95, "contador": {"sospechosos": 0, "descartados": 75, "recuperados": 7, "confirmados": 12, "decesos": 1}}, "ch": {"porcentaje": {"sospechosos": "21.16", "descartados": "69.31", "recuperados": "0.53", "confirmados": "7.94", "decesos": "1.06"}, "total": 189, "contador": {"sospechosos": 40, "descartados": 131, "recuperados": 1, "confirmados": 15, "decesos": 2}}, "sc": {"porcentaje": {"sospechosos": "0.00", "descartados": "49.99", "recuperados": "2.68", "confirmados": "45.72", "decesos": "1.61"}, "total": 4731, "contador": {"sospechosos": 0, "descartados": 2365, "recuperados": 127, "confirmados": 2163, "decesos": 76}}, "pt": {"porcentaje": {"sospechosos": "9.57", "descartados": "69.38", "recuperados": "3.35", "confirmados": "17.22", "decesos": "0.48"}, "total": 209, "contador": {"sospechosos": 20, "descartados": 145, "recuperados": 7, "confirmados": 36, "decesos": 1}}}, "porcentaje": {"sospechosos": "0.70", "descartados": "60.64", "recuperados": "3.55", "confirmados": "33.60", "decesos": "1.51"}, "total": 10036, "fecha": "14/05/20 21:50", "contador": {"sospechosos": 70, "descartados": 6086, "recuperados": 356, "confirmados": 3372, "decesos": 152}}