{"departamento": {"cb": {"total": 3607, "porcentaje": {"confirmados": "65.43", "decesos": "2.80", "sospechosos": "0.00", "descartados": "29.17", "recuperados": "2.61"}, "contador": {"confirmados": 2360, "decesos": 101, "sospechosos": 0, "descartados": 1052, "recuperados": 94}}, "tj": {"total": 316, "porcentaje": {"confirmados": "75.63", "decesos": "2.53", "sospechosos": "1.90", "descartados": "14.87", "recuperados": "5.06"}, "contador": {"confirmados": 239, "decesos": 8, "sospechosos": 6, "descartados": 47, "recuperados": 16}}, "lp": {"total": 3766, "porcentaje": {"confirmados": "41.02", "decesos": "1.46", "sospechosos": "0.11", "descartados": "48.59", "recuperados": "8.82"}, "contador": {"confirmados": 1545, "decesos": 55, "sospechosos": 4, "descartados": 1830, "recuperados": 332}}, "bn": {"total": 3931, "porcentaje": {"confirmados": "91.10", "decesos": "4.53", "sospechosos": "0.00", "descartados": "2.95", "recuperados": "1.42"}, "contador": {"confirmados": 3581, "decesos": 178, "sospechosos": 0, "descartados": 116, "recuperados": 56}}, "or": {"total": 926, "porcentaje": {"confirmados": "50.65", "decesos": "3.89", "sospechosos": "0.00", "descartados": "35.10", "recuperados": "10.37"}, "contador": {"confirmados": 469, "decesos": 36, "sospechosos": 0, "descartados": 325, "recuperados": 96}}, "sc": {"total": 21279, "porcentaje": {"confirmados": "66.57", "decesos": "1.51", "sospechosos": "0.00", "descartados": "11.11", "recuperados": "20.80"}, "contador": {"confirmados": 14165, "decesos": 322, "sospechosos": 0, "descartados": 2365, "recuperados": 4427}}, "pn": {"total": 577, "porcentaje": {"confirmados": "82.50", "decesos": "2.08", "sospechosos": "0.00", "descartados": "13.00", "recuperados": "2.43"}, "contador": {"confirmados": 476, "decesos": 12, "sospechosos": 0, "descartados": 75, "recuperados": 14}}, "ch": {"total": 455, "porcentaje": {"confirmados": "55.60", "decesos": "3.30", "sospechosos": "8.79", "descartados": "28.79", "recuperados": "3.52"}, "contador": {"confirmados": 253, "decesos": 15, "sospechosos": 40, "descartados": 131, "recuperados": 16}}, "pt": {"total": 637, "porcentaje": {"confirmados": "66.56", "decesos": "2.04", "sospechosos": "3.14", "descartados": "22.76", "recuperados": "5.49"}, "contador": {"confirmados": 424, "decesos": 13, "sospechosos": 20, "descartados": 145, "recuperados": 35}}}, "total": 35494, "fecha": "20/06/20 21:50", "porcentaje": {"confirmados": "66.24", "decesos": "2.08", "sospechosos": "0.20", "descartados": "17.15", "recuperados": "14.33"}, "contador": {"confirmados": 23512, "decesos": 740, "sospechosos": 70, "descartados": 6086, "recuperados": 5086}}